{"licNum": "10638", "npi": "1851801955", "credential": "DMD", "class": "Dentist", "specialization": "", "gender": "F", "updated": "10/4/2017", "name": {"first": "MAE", "last": "LANGURI", "middle": "SEDAGHATI"}, "orgName": "", "tin": "1851801955106", "loc": {"lat": 36.15, "lon": -85.5}, "addr": {"mail": {"street_1": "955 MELROSE DR", "city": "COOKEVILLE", "state": "TN", "zip": "385011556", "zip5": "38501", "phone": "4142362207"}, "bus": {"street_1": "694 S WILLOW AVE", "city": "COOKEVILLE", "state": "TN", "zip": "385013882", "zip5": "38501", "phone": "9312786793", "fax": "4142362207"}}}