{"licNum": "10814", "npi": "1700370228", "credential": "DMD", "class": "Dentist", "specialization": "General Practice", "gender": "M", "updated": "6/18/2018", "name": {"first": "BRYAN", "last": "MAINHARDT", "middle": "EDWARD", "prefix": "DR."}, "orgName": "", "tin": "1700370228108", "loc": {"lat": 35.85, "lon": -86.39}, "addr": {"mail": {"street_1": "3343 MEMORIAL BLVD APT B221", "city": "MURFREESBORO", "state": "TN", "zip": "371295424", "zip5": "37129", "phone": "9315388000"}, "bus": {"street_1": "125 WENDELWOOD DR STE B", "city": "MURFREESBORO", "state": "TN", "zip": "371293746", "zip5": "37129", "phone": "6159041585"}}}