{"licNum": "12012994A", "npi": "1316424559", "credential": "DDS", "class": "Dentist", "specialization": "", "gender": "F", "updated": "7/20/2018", "name": {"first": "BRITTANY", "last": "NEFF", "middle": "WOSCHITZ", "prefix": "DR."}, "orgName": "", "tin": "1316424559120", "loc": {"lat": 39.82, "lon": -84.88}, "addr": {"mail": {"street_1": "9885 E 116TH ST STE 200", "city": "FISHERS", "state": "IN", "zip": "460379242", "zip5": "46037"}, "bus": {"street_1": "1923 CHESTER BLVD", "city": "RICHMOND", "state": "IN", "zip": "47374", "zip5": "47374", "phone": "7658315028"}}}