{"licNum": "12011980A", "npi": "1609214535", "credential": "D.D.S.", "class": "Dentist", "specialization": "General Practice", "gender": "F", "updated": "6/13/2013", "name": {"first": "ALLISON", "last": "GIBSON", "middle": "NICOLE", "prefix": "DR."}, "orgName": "", "tin": "1609214535120", "loc": {"lat": 40.47, "lon": -86.13}, "addr": {"mail": {"street_1": "2302 S DIXON RD", "street_2": "SUITE125", "city": "KOKOMO", "state": "IN", "zip": "469026424", "zip5": "46902", "phone": "7654539389"}, "bus": {"street_1": "2302 S DIXON RD", "street_2": "SUITE125", "city": "KOKOMO", "state": "IN", "zip": "469026424", "zip5": "46902", "phone": "7654539389"}}}