{"licNum": "1229", "npi": "1538357769", "credential": "DDS", "class": "Dentist", "specialization": "General Practice", "gender": "M", "updated": "10/12/2007", "name": {"first": "JEFFREY", "last": "BARTLEY", "middle": "JAMES", "prefix": "DR."}, "orgName": "", "tin": "1538357769122", "loc": {"lat": 59.82, "lon": -151.59}, "addr": {"mail": {"street_1": "PO BOX 1011", "city": "HOMER", "state": "AK", "zip": "996031011", "zip5": "99603", "phone": "9072263700", "fax": "9072263702"}, "bus": {"street_1": "34115 STERLING HWY", "city": "ANCHOR POINT", "state": "AK", "zip": "99556", "zip5": "99556", "phone": "9072263700", "fax": "9072263702"}}}