{"licNum": "1282", "npi": "1083868830", "credential": "D.M.D.", "class": "Dentist", "specialization": "", "gender": "M", "updated": "11/6/2008", "name": {"first": "GUY", "last": "BURK", "middle": "J"}, "orgName": "", "tin": "1083868830128", "loc": {"lat": 61.18, "lon": -149.88}, "addr": {"mail": {"street_1": "2805 DAWSON ST", "street_2": "STE 101", "city": "ANCHORAGE", "state": "AK", "zip": "995033800", "zip5": "99503", "phone": "9075626456", "fax": "9075620009"}, "bus": {"street_1": "2805 DAWSON ST", "street_2": "STE 101", "city": "ANCHORAGE", "state": "AK", "zip": "995033800", "zip5": "99503", "phone": "9075626456", "fax": "9075620009"}}}