{"licNum": "13751", "npi": "1831216480", "credential": "\"DDS,PC\"", "class": "Dentist", "specialization": "General Practice", "gender": "M", "updated": "7/8/2007", "name": {"first": "MARK", "last": "HALBOTH", "middle": "JOHN", "prefix": "DR."}, "orgName": "", "tin": "1831216480137", "loc": {"lat": 42.39, "lon": -83.37}, "addr": {"mail": {"street_1": "36000 5 MILE RD", "city": "LIVONIA", "state": "MI", "zip": "481541918", "zip5": "48154", "phone": "7344643430", "fax": "7344646206"}, "bus": {"street_1": "36000 5 MILE RD", "city": "LIVONIA", "state": "MI", "zip": "481541918", "zip5": "48154", "phone": "7344643430", "fax": "7344646206"}}}