{"licNum": "1477796100", "npi": "1477796100", "credential": "\"D.D.S., M.D.\"", "class": "Dentist", "specialization": "Oral and Maxillofacial Surgery", "gender": "M", "updated": "2/13/2017", "name": {"first": "JAMES", "last": "LEWALLEN", "middle": "BRADFORD", "prefix": "DR."}, "orgName": "", "tin": "1477796100615", "loc": {"lat": 35.92, "lon": -86.84}, "addr": {"mail": {"street_1": "3000 STANSBERRY LN", "street_2": "SUITE 101", "city": "FRANKLIN", "state": "TN", "zip": "370695125", "zip5": "37069", "phone": "6155910919", "fax": "6155996762"}, "bus": {"street_1": "3000 STANSBERRY LN", "street_2": "SUITE 101", "city": "FRANKLIN", "state": "TN", "zip": "370695125", "zip5": "37069", "phone": "6155910919", "fax": "6155996762"}}}