{"licNum": "1583", "npi": "1386703692", "credential": "\"OD, DDS\"", "class": "Dentist", "specialization": "", "gender": "M", "updated": "9/11/2007", "name": {"first": "YUNG", "last": "LEE"}, "orgName": "", "tin": "1386703692158", "loc": {"lat": 33.27, "lon": -111.94}, "addr": {"mail": {"street_1": "11103 WEST AVE", "street_2": "SUITE 6", "city": "SAN ANTONIO", "state": "TX", "zip": "782131370", "zip5": "78213", "phone": "2105246509", "fax": "2105246587"}, "bus": {"street_1": "3111 W CHANDLER BLVD", "street_2": "SUITE 1124", "city": "CHANDLER", "state": "AZ", "zip": "852265071", "zip5": "85226", "phone": "4807829380"}}}