{"licNum": "17904", "npi": "1073545810", "credential": "DDS", "class": "Dentist", "specialization": "General Practice", "gender": "F", "updated": "7/8/2007", "name": {"first": "TARA", "last": "MEACHUM", "middle": "LYNN", "prefix": "DR."}, "orgName": "", "tin": "1073545810179", "loc": {"lat": 43.17, "lon": -85.25}, "addr": {"mail": {"street_1": "4241 WELLINGTON CT", "city": "ROCKFORD", "state": "MI", "zip": "49341", "zip5": "49341", "phone": "6163042238", "fax": "6167540519"}, "bus": {"street_1": "117 W CASS ST", "street_2": "GREENVILLE FAMILY DENTAL", "city": "GREENVILLE", "state": "MI", "zip": "48838", "zip5": "48838", "phone": "6167548631", "fax": "6167540519"}}}