{"licNum": "1812", "npi": "1871618652", "credential": "DDS", "class": "Dentist", "specialization": "General Practice", "gender": "M", "updated": "7/8/2007", "name": {"first": "LARY", "last": "GEORGE", "middle": "COMPTON", "suffix": "SR."}, "orgName": "", "tin": "1871618652181", "loc": {"lat": 35.05, "lon": -93.39}, "addr": {"mail": {"street_1": "PO BOX 57", "city": "DANVILLE", "state": "AR", "zip": "72833", "zip5": "72833", "phone": "4794952910", "fax": "4794953208"}, "bus": {"street_1": "109 EAST 9TH", "city": "DANVILLE", "state": "AR", "zip": "72833", "zip5": "72833", "phone": "4794952910", "fax": "4794953208"}}}