{"licNum": "2901022573", "npi": "1740772656", "credential": "DDS", "class": "Dentist", "specialization": "General Practice", "gender": "F", "updated": "2/5/2019", "name": {"first": "COLLEEN", "last": "ALLEN", "middle": "ROSE", "prefix": "DR."}, "orgName": "", "tin": "1740772656290", "loc": {"lat": 42.2, "lon": -83.48}, "addr": {"mail": {"street_1": "14474 OXFORD", "city": "PLYMOUTH", "state": "MI", "zip": "481702674", "zip5": "48170", "phone": "7344172788"}, "bus": {"street_1": "9840 HAGGERTY RD", "city": "BELLEVILLE", "state": "MI", "zip": "48111", "zip5": "48111", "phone": "7346974400"}}}