{"licNum": "2901016479", "npi": "1114936754", "credential": "DDS", "class": "Dentist", "specialization": "General Practice", "gender": "M", "updated": "7/8/2007", "name": {"first": "KENNETH", "last": "EGGER", "middle": "LEON", "prefix": "DR.", "suffix": "JR."}, "orgName": "", "tin": "1114936754290", "loc": {"lat": 43.59, "lon": -84.77}, "addr": {"mail": {"street_1": "900 E BELLOWS ST", "city": "MOUNT PLEASANT", "state": "MI", "zip": "488583904", "zip5": "48858", "phone": "9897733560", "fax": "9897739081"}, "bus": {"street_1": "900 E BELLOWS ST", "city": "MOUNT PLEASANT", "state": "MI", "zip": "488583904", "zip5": "48858", "phone": "9897733560", "fax": "9897739081"}}}