{"licNum": "2901022063", "npi": "1285181016", "credential": "D.D.S.", "class": "Dentist", "specialization": "General Practice", "gender": "M", "updated": "9/9/2016", "name": {"first": "LOUISON", "last": "MANNINGHAM", "middle": "LEONARD", "prefix": "DR.", "suffix": "JR."}, "orgName": "", "tin": "1285181016290", "loc": {"lat": 42.7, "lon": -84.55}, "addr": {"mail": {"street_1": "4911 W ST JOE HWY", "city": "LANSING", "state": "MI", "zip": "489174088", "zip5": "48917", "phone": "5173211848"}, "bus": {"street_1": "4911 W ST JOE HWY", "city": "LANSING", "state": "MI", "zip": "489174088", "zip5": "48917", "phone": "5173211848"}}}