{"licNum": "2901018439", "npi": "1184804676", "credential": "D.M.D", "class": "Dentist", "specialization": "", "gender": "F", "updated": "11/13/2007", "name": {"first": "SHIKHA", "last": "BHATNAGAR", "prefix": "DR."}, "orgName": "", "tin": "1184804676290", "loc": {"lat": 42.58, "lon": -83.14}, "addr": {"mail": {"street_1": "755 W BIG BEAVER RD", "street_2": "SUITE 415", "city": "TROY", "state": "MI", "zip": "480844900", "zip5": "48084", "phone": "2483621100", "fax": "2483622324"}, "bus": {"street_1": "755 W BIG BEAVER RD", "street_2": "SUITE 415", "city": "TROY", "state": "MI", "zip": "480844900", "zip5": "48084", "phone": "2483621100", "fax": "2483622324"}}}