{"licNum": "2901015826", "npi": "1083651970", "credential": "DDS", "class": "Dentist", "specialization": "General Practice", "gender": "M", "updated": "7/8/2007", "name": {"first": "DARAN", "last": "LANSKY", "middle": "FRANCIS", "prefix": "DR."}, "orgName": "", "tin": "1083651970290", "loc": {"lat": 42.5, "lon": -83.15}, "addr": {"mail": {"street_1": "25571 WOODWARD AVE", "city": "ROYAL OAK", "state": "MI", "zip": "480670905", "zip5": "48067", "phone": "2483994742", "fax": "2483994748"}, "bus": {"street_1": "25571 WOODWARD AVE", "city": "ROYAL OAK", "state": "MI", "zip": "480670905", "zip5": "48067", "phone": "2483994742", "fax": "2483994748"}}}