{"licNum": "2901600179", "npi": "1366002289", "credential": "DDS", "class": "Dentist", "specialization": "General Practice", "gender": "M", "updated": "6/13/2019", "name": {"first": "SAILESH", "last": "RAMALINGAM"}, "orgName": "", "tin": "1366002289290", "loc": {"lat": 42.22, "lon": -83.26}, "addr": {"mail": {"street_1": "2119 CHAPS", "city": "TROY", "state": "MI", "zip": "480855520", "zip5": "48085", "phone": "2486196837"}, "bus": {"street_1": "9115 TELEGRAPH RD", "city": "TAYLOR", "state": "MI", "zip": "481802365", "zip5": "48180", "phone": "3139181788"}}}