{"licNum": "2901600124", "npi": "1780245944", "credential": "", "class": "Dentist", "specialization": "General Practice", "gender": "F", "updated": "6/27/2019", "name": {"first": "LAUREN", "last": "LARSON", "middle": "JESSICA"}, "orgName": "", "tin": "1780245944290", "loc": {"lat": 42.27, "lon": -83.73}, "addr": {"mail": {"street_1": "828 W HURON ST", "city": "ANN ARBOR", "state": "MI", "zip": "481034214", "zip5": "48103"}, "bus": {"street_1": "828 W HURON ST", "city": "ANN ARBOR", "state": "MI", "zip": "481034214", "zip5": "48103", "phone": "7349940909", "fax": "7349940910"}}}