{"licNum": "2901020512", "npi": "1689016982", "credential": "\"D.D.S., M.S.\"", "class": "Dentist", "specialization": "Orthodontics and Dentofacial Orthopedics", "gender": "M", "updated": "7/27/2013", "name": {"first": "JEREK", "last": "PETROUS", "middle": "BRADFORD", "prefix": "DR."}, "orgName": "", "tin": "1689016982290", "loc": {"lat": 42.5, "lon": -83.1}, "addr": {"mail": {"street_1": "30201 DEQUINDRE RD", "city": "MADISON HEIGHTS", "state": "MI", "zip": "480712284", "zip5": "48071", "phone": "2482194154", "fax": "2485885610"}, "bus": {"street_1": "30201 DEQUINDRE RD", "city": "MADISON HEIGHTS", "state": "MI", "zip": "480712284", "zip5": "48071", "phone": "2482194154", "fax": "2485885610"}}}