{"licNum": "2901009411", "npi": "1649469214", "credential": "D.D.S.", "class": "Dentist", "specialization": "", "gender": "M", "updated": "10/19/2007", "name": {"first": "JOHN", "last": "GOBETTI", "middle": "PAUL", "prefix": "DR."}, "orgName": "", "tin": "1649469214290", "loc": {"lat": 42.27, "lon": -83.73}, "addr": {"mail": {"street_1": "169 BARTON DR", "city": "ANN ARBOR", "state": "MI", "zip": "481051142", "zip5": "48105", "phone": "7346633651", "fax": "7346682089"}, "bus": {"street_1": "169 BARTON DR", "city": "ANN ARBOR", "state": "MI", "zip": "481051142", "zip5": "48105", "phone": "7346633651", "fax": "7346682089"}}}