{"licNum": "2901010631", "npi": "1942275904", "credential": "DDS", "class": "Dentist", "specialization": "General Practice", "gender": "M", "updated": "1/22/2008", "name": {"first": "THOMAS", "last": "BENNETT", "middle": "SCOTT"}, "orgName": "", "tin": "1942275904290", "loc": {"lat": 42.21, "lon": -85.89}, "addr": {"mail": {"street_1": "612 W MICHIGAN AVE", "city": "PAW PAW", "state": "MI", "zip": "490791041", "zip5": "49079", "phone": "2696573121", "fax": "2696575865"}, "bus": {"street_1": "612 W MICHIGAN AVE", "city": "PAW PAW", "state": "MI", "zip": "490791041", "zip5": "49079", "phone": "2696573121", "fax": "2696575865"}}}