{"licNum": "2901022618", "npi": "1437640943", "credential": "DDS", "class": "Dentist", "specialization": "", "gender": "F", "updated": "9/27/2018", "name": {"first": "CAITLIN", "last": "PARSON", "middle": "MARIE", "prefix": "DR."}, "orgName": "", "tin": "1437640943290", "loc": {"lat": 43.39, "lon": -86.34}, "addr": {"mail": {"street_1": "1671 LAKEWOOD RD", "city": "TWIN LAKE", "state": "MI", "zip": "494578976", "zip5": "49457", "phone": "2312153890"}, "bus": {"street_1": "116 W COLBY ST", "city": "WHITEHALL", "state": "MI", "zip": "494611083", "zip5": "49461", "phone": "2318932915"}}}