{"licNum": "2901011799", "npi": "1912117128", "credential": "DDS", "class": "Dentist", "specialization": "General Practice", "gender": "M", "updated": "7/8/2007", "name": {"first": "BRADLEY", "last": "DYKSTRA", "middle": "ALAN", "prefix": "DR."}, "orgName": "", "tin": "1912117128290", "loc": {"lat": 42.86, "lon": -85.86}, "addr": {"mail": {"street_1": "3250 CENTRAL BLVD", "city": "HUDSONVILLE", "state": "MI", "zip": "494261439", "zip5": "49426", "phone": "6166696600"}, "bus": {"street_1": "3250 CENTRAL BLVD", "city": "HUDSONVILLE", "state": "MI", "zip": "494261439", "zip5": "49426", "phone": "6166696600"}}}