{"licNum": "3140", "npi": "1780032029", "credential": "D.M.D.", "class": "Dentist", "specialization": "", "gender": "M", "updated": "5/26/2016", "name": {"first": "BRUCE", "last": "BAUMAN", "middle": "LEONARD", "prefix": "DR."}, "orgName": "", "tin": "1780032029314", "loc": {"lat": 33.72, "lon": -112.08}, "addr": {"mail": {"street_1": "2550 W UNION HILLS DR", "street_2": "SUITE 202", "city": "PHOENIX", "state": "AZ", "zip": "850275163", "zip5": "85027", "phone": "8888338441"}, "bus": {"street_1": "2550 W UNION HILLS DR", "street_2": "SUITE 202", "city": "PHOENIX", "state": "AZ", "zip": "850275163", "zip5": "85027", "phone": "8888338441"}}}