{"licNum": "3378", "npi": "1871597344", "credential": "D.D.S.", "class": "Dentist", "specialization": "General Practice", "gender": "M", "updated": "7/8/2007", "name": {"first": "FREDERICK", "last": "DEAL", "middle": "G.S.", "prefix": "DR."}, "orgName": "", "tin": "1871597344337", "loc": {"lat": 36.36, "lon": -94.28}, "addr": {"mail": {"street_1": "431 W CENTERTON BLVD", "city": "CENTERTON", "state": "AR", "zip": "727198701", "zip5": "72719", "phone": "4797951101", "fax": "4797950242"}, "bus": {"street_1": "431 W CENTERTON BLVD", "city": "CENTERTON", "state": "AR", "zip": "727198701", "zip5": "72719", "phone": "4797951101", "fax": "4797950242"}}}