{"licNum": "3803", "npi": "1427231448", "credential": "D.M.D.", "class": "Dentist", "specialization": "General Practice", "gender": "M", "updated": "12/12/2007", "name": {"first": "STEPHEN", "last": "HARDY", "middle": "FRANCIS", "prefix": "DR."}, "orgName": "", "tin": "1427231448380", "loc": {"lat": 33.63, "lon": -112.09}, "addr": {"mail": {"street_1": "1930 W THUNDERBIRD RD STE 116", "city": "PHOENIX", "state": "AZ", "zip": "850236369", "zip5": "85023", "phone": "6029933744", "fax": "6029933745"}, "bus": {"street_1": "1930 W THUNDERBIRD RD STE 116", "city": "PHOENIX", "state": "AZ", "zip": "850236369", "zip5": "85023", "phone": "6029933744", "fax": "6029933745"}}}