{"licNum": "4001", "npi": "1710393517", "credential": "D.D.S.", "class": "Dentist", "specialization": "", "gender": "M", "updated": "7/1/2014", "name": {"first": "CHASE", "last": "DIEMER", "middle": "CONWAY", "prefix": "DR."}, "orgName": "", "tin": "1710393517400", "loc": {"lat": 34.72, "lon": -92.35}, "addr": {"mail": {"street_1": "15208 BAUCH LN", "city": "LITTLE ROCK", "state": "AR", "zip": "722065787", "zip5": "72206", "phone": "5018311980"}, "bus": {"street_1": "15208 BAUCH LN", "city": "LITTLE ROCK", "state": "AR", "zip": "722065787", "zip5": "72206", "phone": "5018311980"}}}