{"licNum": "4057", "npi": "1124401336", "credential": "DDS", "class": "Dentist", "specialization": "", "gender": "M", "updated": "7/7/2015", "name": {"first": "MATTHEW", "last": "REITH", "middle": "ROBERT"}, "orgName": "", "tin": "1124401336405", "loc": {"lat": 36.26, "lon": -94.13}, "addr": {"mail": {"street_1": "125B S BLOOMINGTON ST", "city": "LOWELL", "state": "AR", "zip": "727459493", "zip5": "72745", "phone": "4796515888"}, "bus": {"street_1": "125B S BLOOMINGTON ST", "city": "LOWELL", "state": "AR", "zip": "727459493", "zip5": "72745", "phone": "4796515888"}}}