{"licNum": "4676", "npi": "1376788489", "credential": "DDS", "class": "Dentist", "specialization": "General Practice", "gender": "M", "updated": "1/29/2009", "name": {"first": "RICHARD", "last": "JOHNSON", "middle": "A", "prefix": "DR."}, "orgName": "", "tin": "1376788489467", "loc": {"lat": 32.22, "lon": -110.82}, "addr": {"mail": {"street_1": "8230 E BROADWAY BLVD # 1", "city": "TUCSON", "state": "AZ", "zip": "857104044", "zip5": "85710", "phone": "5202900120", "fax": "5202960558"}, "bus": {"street_1": "8230 E BROADWAY BLVD", "street_2": "W-1", "city": "TUCSON", "state": "AZ", "zip": "857104044", "zip5": "85710", "phone": "5202900120", "fax": "5202960558"}}}