{"licNum": "7329", "npi": "1568565612", "credential": "DDS", "class": "Dentist", "specialization": "Pediatric Dentistry", "gender": "M", "updated": "7/8/2007", "name": {"first": "PETER", "last": "MIELKE", "middle": "HERMANN"}, "orgName": "", "tin": "1568565612732", "loc": {"lat": 44.94, "lon": -93.1}, "addr": {"mail": {"street_1": "1675 BEAM AVE", "street_2": "#202", "city": "MAPLEWOOD", "state": "MN", "zip": "55109", "zip5": "55109", "phone": "6517799002", "fax": "6517799802"}, "bus": {"street_1": "1675 BEAM AVE", "street_2": "#202", "city": "MAPLEWOOD", "state": "MN", "zip": "55109", "zip5": "55109", "phone": "6517799002", "fax": "6517799802"}}}