{"licNum": "7425", "npi": "1649251828", "credential": "DMD", "class": "Dentist", "specialization": "Endodontics", "gender": "M", "updated": "7/8/2007", "name": {"first": "KEITH", "last": "FOSTER", "middle": "H.", "prefix": "DR."}, "orgName": "", "tin": "1649251828742", "loc": {"lat": 35.74, "lon": -83.97}, "addr": {"mail": {"street_1": "206 SIMMONS ST", "city": "MARYVILLE", "state": "TN", "zip": "378014750", "zip5": "37801", "phone": "8659840104", "fax": "8659840188"}, "bus": {"street_1": "206 SIMMONS ST", "city": "MARYVILLE", "state": "TN", "zip": "378014750", "zip5": "37801", "phone": "8659840104", "fax": "8659840188"}}}