{"licNum": "7490", "npi": "1881794972", "credential": "D.D.S.", "class": "Dentist", "specialization": "General Practice", "gender": "M", "updated": "7/8/2007", "name": {"first": "ROBERT", "last": "SCHMIDLE", "middle": "MICHAEL", "prefix": "DR."}, "orgName": "", "tin": "1881794972749", "loc": {"lat": 36.33, "lon": -86.7}, "addr": {"mail": {"street_1": "313A BLUEBIRD DR", "city": "GOODLETTSVILLE", "state": "TN", "zip": "370722303", "zip5": "37072", "phone": "6158591910", "fax": "6158591913"}, "bus": {"street_1": "313A BLUEBIRD DR", "city": "GOODLETTSVILLE", "state": "TN", "zip": "370722303", "zip5": "37072", "phone": "6158591910", "fax": "6158591913"}}}