{"licNum": "8255", "npi": "1669507059", "credential": "DDS", "class": "Dentist", "specialization": "", "gender": "M", "updated": "7/8/2007", "name": {"first": "PETER", "last": "FERRARI", "middle": "J", "prefix": "MR."}, "orgName": "", "tin": "1669507059825", "loc": {"lat": 41.53, "lon": -87.26}, "addr": {"mail": {"street_1": "1801 WOODMERE DR", "city": "VALPARAISO", "state": "IN", "zip": "463831645", "zip5": "46383", "phone": "2194649774", "fax": "2195319338"}, "bus": {"street_1": "1005 LINCOLN ST", "city": "HOBART", "state": "IN", "zip": "463426037", "zip5": "46342", "phone": "2199424858", "fax": "2199424036"}}}