{"licNum": "8971", "npi": "1023252939", "credential": "D.D.S.", "class": "Dentist", "specialization": "General Practice", "gender": "M", "updated": "1/21/2013", "name": {"first": "RAJAN", "last": "KSHATRI", "prefix": "DR."}, "orgName": "", "tin": "1023252939897", "loc": {"lat": 36.25, "lon": -86.69}, "addr": {"mail": {"street_1": "231 W OLD HICKORY BLVD", "street_2": "SUITE A", "city": "MADISON", "state": "TN", "zip": "371153664", "zip5": "37115", "phone": "6158655750", "fax": "6158688638"}, "bus": {"street_1": "231 W OLD HICKORY BLVD", "street_2": "SUITE A", "city": "MADISON", "state": "TN", "zip": "371153664", "zip5": "37115", "phone": "6158655750", "fax": "6158688638"}}}