{"licNum": "9657", "npi": "1053847319", "credential": "", "class": "Dentist", "specialization": "General Practice", "gender": "F", "updated": "5/21/2019", "name": {"first": "AMANDA", "last": "GIRARDI"}, "orgName": "", "tin": "1053847319965", "loc": {"lat": 33.34, "lon": -112.06}, "addr": {"mail": {"street_1": "4726 E VERBENA DR", "city": "PHOENIX", "state": "AZ", "zip": "850444974", "zip5": "85044", "phone": "2094812544"}, "bus": {"street_1": "4726 E VERBENA DR", "city": "PHOENIX", "state": "AZ", "zip": "85044", "zip5": "85044", "phone": "2094812544"}}}