{"licNum": "D009000", "npi": "1356757157", "credential": "", "class": "Dentist", "specialization": "Orthodontics and Dentofacial Orthopedics", "gender": "M", "updated": "8/19/2014", "name": {"first": "PAYAM", "last": "OWTAD", "prefix": "DR."}, "orgName": "", "tin": "1356757157D00", "loc": {"lat": 33.39, "lon": -111.71}, "addr": {"mail": {"street_1": "6745 E SUPERSTITION SPRINGS BLVD APT 2022", "city": "MESA", "state": "AZ", "zip": "852064317", "zip5": "85206"}, "bus": {"street_1": "6745 E SUPERSTITION SPRINGS BLVD APT 2022", "city": "MESA", "state": "AZ", "zip": "852064317", "zip5": "85206", "phone": "6502753843"}}}