{"licNum": "D009010", "npi": "1669756342", "credential": "DDS", "class": "Dentist", "specialization": "Pediatric Dentistry", "gender": "M", "updated": "7/31/2014", "name": {"first": "STEPHEN", "last": "STANFIELD", "middle": "RICHARD", "prefix": "DR."}, "orgName": "", "tin": "1669756342D00", "loc": {"lat": 33.69, "lon": -112.0}, "addr": {"mail": {"street_1": "21001 N TATUM BLVD", "city": "PHOENIX", "state": "AZ", "zip": "850504206", "zip5": "85050", "phone": "4805155437"}, "bus": {"street_1": "21001 N TATUM BLVD", "city": "PHOENIX", "state": "AZ", "zip": "850504206", "zip5": "85050", "phone": "4805155437"}}}