{"licNum": "D11970", "npi": "1356316632", "credential": "D.D.S.", "class": "Dentist", "specialization": "General Practice", "gender": "M", "updated": "7/8/2007", "name": {"first": "FRANCOIS", "last": "GERBER"}, "orgName": "", "tin": "1356316632D11", "loc": {"lat": 46.78, "lon": -92.11}, "addr": {"mail": {"street_1": "4325 GRAND AVE", "street_2": "SUITE 2", "city": "DULUTH", "state": "MN", "zip": "558072730", "zip5": "55807", "phone": "2186287036", "fax": "2186246594"}, "bus": {"street_1": "4325 GRAND AVE", "street_2": "SUITE 2", "city": "DULUTH", "state": "MN", "zip": "558072730", "zip5": "55807", "phone": "2186287036", "fax": "2186246594"}}}