{"licNum": "D13819", "npi": "1801324843", "credential": "DDS", "class": "Dentist", "specialization": "General Practice", "gender": "M", "updated": "6/2/2017", "name": {"first": "JAGADISH", "last": "MARAHATTA"}, "orgName": "", "tin": "1801324843D13", "loc": {"lat": 44.96, "lon": -93.26}, "addr": {"mail": {"street_1": "1014 27TH AVE SE APT B", "city": "MINNEAPOLIS", "state": "MN", "zip": "554142757", "zip5": "55414", "phone": "(612) 916-0946"}, "bus": {"street_1": "512 66TH AVE N", "city": "BROOKLYN CENTER", "state": "MN", "zip": "554301643", "zip5": "55430", "phone": "7635603334"}}}