{"licNum": "D1695", "npi": "1164645941", "credential": "DMD", "class": "Dentist", "specialization": "General Practice", "gender": "M", "updated": "7/8/2007", "name": {"first": "STEVEN", "last": "ELCOCK", "middle": "CHARLES", "prefix": "DR."}, "orgName": "", "tin": "1164645941D16", "loc": {"lat": 33.49, "lon": -112.21}, "addr": {"mail": {"street_1": "6535 W CAMELBACK RD", "street_2": "SUITE 4", "city": "PHOENIX", "state": "AZ", "zip": "850331608", "zip5": "85033", "phone": "6238481201", "fax": "6238481236"}, "bus": {"street_1": "6535 W CAMELBACK RD", "street_2": "SUITE 4", "city": "PHOENIX", "state": "AZ", "zip": "850331608", "zip5": "85033", "phone": "6238481201", "fax": "6238481236"}}}