{"licNum": "D1799", "npi": "1891832796", "credential": "D.D.S.", "class": "Dentist", "specialization": "General Practice", "gender": "M", "updated": "7/8/2007", "name": {"first": "JOHN", "last": "MCLAUGHLIN", "middle": "MERLE", "prefix": "DR."}, "orgName": "", "tin": "1891832796D17", "loc": {"lat": 35.29, "lon": -111.32}, "addr": {"mail": {"street_1": "1515 E CEDAR AVE", "street_2": "SUITE C-1", "city": "FLAGSTAFF", "state": "AZ", "zip": "860041600", "zip5": "86004", "phone": "9287744831", "fax": "9282146073"}, "bus": {"street_1": "1515 E CEDAR AVE", "street_2": "SUITE C-1", "city": "FLAGSTAFF", "state": "AZ", "zip": "860041600", "zip5": "86004", "phone": "9287744831", "fax": "9282146073"}}}