{"licNum": "D2703", "npi": "1215017595", "credential": "DDS", "class": "Dentist", "specialization": "General Practice", "gender": "M", "updated": "7/8/2007", "name": {"first": "JOHN", "last": "DINSMORE", "middle": "PORTER", "prefix": "MR."}, "orgName": "", "tin": "1215017595D27", "loc": {"lat": 35.97, "lon": -83.94}, "addr": {"mail": {"street_1": "10533 LAKECOVE WAY", "city": "KNOXVILLE", "state": "TN", "zip": "379225530", "zip5": "37922", "phone": "8659662865", "fax": "8659662865"}, "bus": {"street_1": "117 HUXLEY RD # B-2", "city": "KNOXVILLE", "state": "TN", "zip": "379223179", "zip5": "37922", "phone": "8656935030", "fax": "8656935024"}}}