{"licNum": "D5718", "npi": "1295068351", "credential": "\"DDS,MS\"", "class": "Dentist", "specialization": "Orthodontics and Dentofacial Orthopedics", "gender": "M", "updated": "1/21/2014", "name": {"first": "C.", "last": "MURPHY", "middle": "CHRISTOPHER"}, "orgName": "", "tin": "1295068351D57", "loc": {"lat": 33.67, "lon": -111.95}, "addr": {"mail": {"street_1": "4429 E SPARKLING LN", "city": "PARADISE VALLEY", "state": "AZ", "zip": "852532852", "zip5": "85253", "phone": "4802207333"}, "bus": {"street_1": "5355 E HIGH ST STE 105", "city": "PHOENIX", "state": "AZ", "zip": "850545481", "zip5": "85054", "phone": "6024820022"}}}