{"licNum": "D6969", "npi": "1366418162", "credential": "D.M.D.", "class": "Dentist", "specialization": "", "gender": "M", "updated": "11/2/2016", "name": {"first": "KENT", "last": "SPURLING", "middle": "JAMES", "prefix": "DR."}, "orgName": "", "tin": "1366418162D69", "loc": {"lat": 33.44, "lon": -111.76}, "addr": {"mail": {"street_1": "2727 E MCKELLIPS RD", "street_2": "SUITE 101", "city": "MESA", "state": "AZ", "zip": "85213", "zip5": "85213", "phone": "4806126352", "fax": "4808930596"}, "bus": {"street_1": "2727 E. MCKELLIPS RD", "street_2": "SUITE 101", "city": "MESA", "state": "AZ", "zip": "85213", "zip5": "85213", "phone": "4806126352", "fax": "4808930596"}}}