{"licNum": "D7114", "npi": "1053465682", "credential": "DDS", "class": "Dentist", "specialization": "General Practice", "gender": "M", "updated": "7/8/2007", "name": {"first": "JAMES", "last": "MCDONALD", "middle": "STANLEY", "prefix": "DR."}, "orgName": "", "tin": "1053465682D71", "loc": {"lat": 47.93, "lon": -97.01}, "addr": {"mail": {"street_1": "1421 CENTRAL AVE NW", "city": "EAST GRAND FORKS", "state": "MN", "zip": "567211613", "zip5": "56721", "phone": "2187733010", "fax": "2187739780"}, "bus": {"street_1": "1421 CENTRAL AVE NW", "city": "EAST GRAND FORKS", "state": "MN", "zip": "567211613", "zip5": "56721", "phone": "2187733010", "fax": "2187739780"}}}