{"licNum": "D8006", "npi": "1558672659", "credential": "DDS", "class": "Dentist", "specialization": "Pediatric Dentistry", "gender": "M", "updated": "6/23/2010", "name": {"first": "ROBERT", "last": "BALSMEIER", "prefix": "DR."}, "orgName": "", "tin": "1558672659D80", "loc": {"lat": 33.55, "lon": -112.09}, "addr": {"mail": {"street_1": "1819 W DUNLAP AVE", "street_2": "SUITE 1", "city": "PHOENIX", "state": "AZ", "zip": "850214375", "zip5": "85021", "phone": "6028613333"}, "bus": {"street_1": "1819 W DUNLAP AVE", "street_2": "SUITE 1", "city": "PHOENIX", "state": "AZ", "zip": "850214375", "zip5": "85021", "phone": "6028613333"}}}