{"licNum": "D8139", "npi": "1265457840", "credential": "DDS PA ORTHODONTIST", "class": "Dentist", "specialization": "Orthodontics and Dentofacial Orthopedics", "gender": "M", "updated": "7/8/2007", "name": {"first": "DOUGLAS", "last": "AAKER", "middle": "T", "prefix": "DR."}, "orgName": "", "tin": "1265457840D81", "loc": {"lat": 45.55, "lon": -94.17}, "addr": {"mail": {"street_1": "916 WEST ST GERMAIN STREET", "street_2": "# 113", "city": "ST. CLOUD", "state": "MN", "zip": "56301", "zip5": "56301", "phone": "3202538908", "fax": "3202538920"}, "bus": {"street_1": "916 WEST ST GERMAIN STREET", "street_2": "# 113", "city": "ST. CLOUD", "state": "MN", "zip": "56301", "zip5": "56301", "phone": "3202538908", "fax": "3202538920"}}}