{"licNum": "D8484", "npi": "1154339141", "credential": "DDS", "class": "Dentist", "specialization": "", "gender": "M", "updated": "7/8/2007", "name": {"first": "LARRY", "last": "SCHMID", "middle": "JAMES", "prefix": "DR."}, "orgName": "", "tin": "1154339141D84", "loc": {"lat": 44.73, "lon": -92.85}, "addr": {"mail": {"street_1": "925 HWY 55", "street_2": "STE 104", "city": "HASTINGS", "state": "MN", "zip": "55033", "zip5": "55033", "phone": "6514375340", "fax": "6514373780"}, "bus": {"street_1": "925 HWY 55", "street_2": "STE 104", "city": "HASTINGS", "state": "MN", "zip": "55033", "zip5": "55033", "phone": "6514375340", "fax": "6514373780"}}}