{"licNum": "DS0000005390", "npi": "1619952314", "credential": "DDS", "class": "Dentist", "specialization": "Oral and Maxillofacial Surgery", "gender": "M", "updated": "12/22/2010", "name": {"first": "JAMES", "last": "ANDERSON", "middle": "GREGORY", "prefix": "DR."}, "orgName": "", "tin": "1619952314DS0", "loc": {"lat": 36.09, "lon": -84.13}, "addr": {"mail": {"street_1": "2130 N CHARLES G SEIVERS BLVD STE 1", "city": "CLINTON", "state": "TN", "zip": "377166705", "zip5": "37716", "phone": "8656224959", "fax": "8652694336"}, "bus": {"street_1": "2130 N CHARLES G SEIVERS BLVD STE 1", "city": "CLINTON", "state": "TN", "zip": "377166705", "zip5": "37716", "phone": "8656224959", "fax": "8652694336"}}}