{"licNum": "DS1704", "npi": "1750456828", "credential": "DDS", "class": "Dentist", "specialization": "", "gender": "M", "updated": "7/8/2007", "name": {"first": "LARRY", "last": "WEISS", "middle": "STEVEN", "prefix": "DR."}, "orgName": "", "tin": "1750456828DS1", "loc": {"lat": 35.1, "lon": -90.0}, "addr": {"mail": {"street_1": "165 MADISON AVE", "street_2": "SUITE 1206", "city": "MEMPHIS", "state": "TN", "zip": "381032740", "zip5": "38103"}, "bus": {"street_1": "165 MADISON AVE", "street_2": "SUITE 1206", "city": "MEMPHIS", "state": "TN", "zip": "381032740", "zip5": "38103", "phone": "9015232999", "fax": "9015267950"}}}