{"licNum": "DS3913", "npi": "1154312437", "credential": "DDS CAGS", "class": "Dentist", "specialization": "Endodontics", "gender": "M", "updated": "7/8/2007", "name": {"first": "PHILLIP", "last": "HEAD", "middle": "WAYNE", "suffix": "SR."}, "orgName": "", "tin": "1154312437DS3", "loc": {"lat": 35.62, "lon": -87.04}, "addr": {"mail": {"street_1": "1324 TROTWOOD AVE", "city": "COLUMBIA", "state": "TN", "zip": "384014750", "zip5": "38401", "phone": "9313885627", "fax": "9313816797"}, "bus": {"street_1": "1324 TROTWOOD AVE", "city": "COLUMBIA", "state": "TN", "zip": "384014750", "zip5": "38401", "phone": "9313885627", "fax": "9313816797"}}}