{"licNum": "DS660", "npi": "1174633093", "credential": "DDS", "class": "Dentist", "specialization": "", "gender": "M", "updated": "7/8/2007", "name": {"first": "EARL", "last": "KEISTER", "middle": "L", "prefix": "DR.", "suffix": "JR."}, "orgName": "", "tin": "1174633093DS6", "loc": {"lat": 35.97, "lon": -83.94}, "addr": {"mail": {"street_1": "PO BOX 5146", "city": "KNOXVILLE", "state": "TN", "zip": "37928", "zip5": "37928", "phone": "8656892185", "fax": "8656892189"}, "bus": {"street_1": "200 MIDLAKE DR", "street_2": "SUITE A", "city": "KNOXVILLE", "state": "TN", "zip": "37918", "zip5": "37918", "phone": "8656892185", "fax": "8656892189"}}}