{"licNum": "TN4666", "npi": "1790715811", "credential": "DDS", "class": "Dentist", "specialization": "General Practice", "gender": "M", "updated": "7/8/2007", "name": {"first": "DAVID", "last": "FEICK", "middle": "ALAN", "prefix": "DR."}, "orgName": "", "tin": "1790715811TN4", "loc": {"lat": 35.92, "lon": -86.84}, "addr": {"mail": {"street_1": "4095 MALLORY LN", "city": "FRANKLIN", "state": "TN", "zip": "370678268", "zip5": "37067", "phone": "6157949401", "fax": "4256967713"}, "bus": {"street_1": "4095 MALLORY LN", "city": "FRANKLIN", "state": "TN", "zip": "370678268", "zip5": "37067", "phone": "6157949401", "fax": "4256967713"}}}