{"licNum": "12009170A", "npi": "1205937943", "credential": "D.D.S.", "class": "Dentist", "specialization": "General Practice", "gender": "M", "updated": "2/17/2012", "name": {"first": "TODD", "last": "WHITLOCK", "middle": "MITCHELL", "prefix": "DR."}, "orgName": "", "tin": "1205937943120", "loc": {"lat": 39.16, "lon": -86.52}, "addr": {"mail": {"street_1": "3671 S SARE RD", "city": "BLOOMINGTON", "state": "IN", "zip": "474014173", "zip5": "47401", "phone": "8123320052", "fax": "8123320128"}, "bus": {"street_1": "3671 S SARE RD", "city": "BLOOMINGTON", "state": "IN", "zip": "474014173", "zip5": "47401", "phone": "8123320052", "fax": "8123320128"}}}