{"licNum": "12010142", "npi": "1548473416", "credential": "D.D.S.", "class": "Dentist", "specialization": "General Practice", "gender": "M", "updated": "7/24/2007", "name": {"first": "RANDALL", "last": "BRUCKEN", "prefix": "DR."}, "orgName": "", "tin": "1548473416120", "loc": {"lat": 40.41, "lon": -86.87}, "addr": {"mail": {"street_1": "1741 CUNNINGHAM ROAD", "city": "SPEEDWAY", "state": "IN", "zip": "46224", "zip5": "46224", "phone": "7657423100"}, "bus": {"street_1": "3711 ROME DRIVE", "street_2": "SUITE A", "city": "LAFAYETTE", "state": "IN", "zip": "47905", "zip5": "47905", "phone": "7657423100", "fax": "7657420152"}}}