{"licNum": "12010651A", "npi": "1841510963", "credential": "\"D.D.S., M.S.\"", "class": "Dentist", "specialization": "Orthodontics and Dentofacial Orthopedics", "gender": "M", "updated": "6/11/2010", "name": {"first": "JASON", "last": "BUNCH", "middle": "K"}, "orgName": "", "tin": "1841510963120", "loc": {"lat": 39.96, "lon": -86.1}, "addr": {"mail": {"street_1": "14555 HAZEL DELL PKWY", "city": "CARMEL", "state": "IN", "zip": "460337000", "zip5": "46033", "phone": "3178159310", "fax": "3178158399"}, "bus": {"street_1": "14555 HAZEL DELL PKWY", "city": "CARMEL", "state": "IN", "zip": "460337000", "zip5": "46033", "phone": "3178159310", "fax": "3178158399"}}}