{"licNum": "12010762A", "npi": "1396955092", "credential": "D.D.S", "class": "Dentist", "specialization": "General Practice", "gender": "M", "updated": "7/1/2016", "name": {"first": "MARK", "last": "STAHL", "middle": "ALAN", "prefix": "DR."}, "orgName": "", "tin": "1396955092120", "loc": {"lat": 39.77, "lon": -86.14}, "addr": {"mail": {"street_1": "1113 WESTFIELD CT W APT C", "city": "INDIANAPOLIS", "state": "IN", "zip": "462201162", "zip5": "46220", "phone": "2067436080"}, "bus": {"street_1": "6919 E 10TH ST", "city": "INDIANAPOLIS", "state": "IN", "zip": "462194893", "zip5": "46219", "phone": "3173588885"}}}