{"licNum": "12069", "npi": "1376792747", "credential": "D.M.D.", "class": "Dentist", "specialization": "General Practice", "gender": "M", "updated": "9/10/2008", "name": {"first": "CALVIN", "last": "BROWN", "middle": "C", "prefix": "DR.", "suffix": "SR."}, "orgName": "", "tin": "1376792747120", "loc": {"lat": 42.38, "lon": -83.1}, "addr": {"mail": {"street_1": "18616 W MCNICHOLS RD", "city": "DETROIT", "state": "MI", "zip": "482194160", "zip5": "48219", "phone": "3135321115", "fax": "3132554523"}, "bus": {"street_1": "18616 W MCNICHOLS RD", "city": "DETROIT", "state": "MI", "zip": "482194160", "zip5": "48219", "phone": "3135321115", "fax": "3132554523"}}}