{"licNum": "12661", "npi": "1407989221", "credential": "D.D.S. P.C", "class": "Dentist", "specialization": "General Practice", "gender": "M", "updated": "7/8/2007", "name": {"first": "WALTER", "last": "SASSACK", "middle": "R"}, "orgName": "", "tin": "1407989221126", "loc": {"lat": 42.16, "lon": -83.21}, "addr": {"mail": {"street_1": "17711 FORT ST", "city": "RIVERVIEW", "state": "MI", "zip": "481936632", "zip5": "48193", "phone": "7342832818", "fax": "7342832888"}, "bus": {"street_1": "17711 FORT ST", "city": "RIVERVIEW", "state": "MI", "zip": "481936632", "zip5": "48193", "phone": "7342832818", "fax": "7342832888"}}}