{"licNum": "12922", "npi": "1861588170", "credential": "D.D.S.", "class": "Dentist", "specialization": "General Practice", "gender": "F", "updated": "7/8/2007", "name": {"first": "ESTER", "last": "SLEUTELBERG", "middle": "ROSALIE", "prefix": "DR."}, "orgName": "", "tin": "1861588170129", "loc": {"lat": 42.46, "lon": -83.18}, "addr": {"mail": {"street_1": "15421 W 9 MILE RD", "city": "OAK PARK", "state": "MI", "zip": "482372516", "zip5": "48237", "phone": "2489682266", "fax": "2489682006"}, "bus": {"street_1": "15421 W 9 MILE RD", "city": "OAK PARK", "state": "MI", "zip": "482372516", "zip5": "48237", "phone": "2489682266", "fax": "2489682006"}}}