{"licNum": "1356803712", "npi": "1356803712", "credential": "", "class": "Dentist", "specialization": "General Practice", "gender": "M", "updated": "6/28/2019", "name": {"first": "JUSTIN", "last": "ELLIS", "middle": "KADE"}, "orgName": "", "tin": "1356803712615", "loc": {"lat": 35.99, "lon": -86.78}, "addr": {"mail": {"street_1": "343 FRANKLIN RD STE 103", "city": "BRENTWOOD", "state": "TN", "zip": "370275250", "zip5": "37027", "phone": "6153431313"}, "bus": {"street_1": "343 FRANKLIN RD STE 103", "city": "BRENTWOOD", "state": "TN", "zip": "37027", "zip5": "37027", "phone": "6153431313"}}}