{"licNum": "1386081628", "npi": "1386081628", "credential": "D.M.D.", "class": "Dentist", "specialization": "Oral and Maxillofacial Surgery", "gender": "M", "updated": "6/16/2018", "name": {"first": "ANDREW", "last": "WICKE", "middle": "EVERETT", "prefix": "DR."}, "orgName": "", "tin": "1386081628615", "loc": {"lat": 36.29, "lon": -86.6}, "addr": {"mail": {"street_1": "131 INDIAN LAKE BLVD STE 100", "city": "HENDERSONVILLE", "state": "TN", "zip": "370756207", "zip5": "37075", "phone": "6158228403", "fax": "6155377696"}, "bus": {"street_1": "131 INDIAN LAKE BLVD STE 100", "city": "HENDERSONVILLE", "state": "TN", "zip": "370756207", "zip5": "37075", "phone": "6158228403", "fax": "6155377696"}}}