{"licNum": "14209", "npi": "1306067400", "credential": "DDS", "class": "Dentist", "specialization": "General Practice", "gender": "M", "updated": "7/8/2007", "name": {"first": "THOMAS", "last": "HAZELTON", "middle": "I", "prefix": "DR."}, "orgName": "", "tin": "1306067400142", "loc": {"lat": 43.52, "lon": -82.74}, "addr": {"mail": {"street_1": "PO BOX 460", "street_2": "2382 BLACK RIVER ST", "city": "DECKERVILLE", "state": "MI", "zip": "48427", "zip5": "48427", "phone": "8103762395", "fax": "8103762305"}, "bus": {"street_1": "2382 BLACK RIVER ST", "city": "DECKERVILLE", "state": "MI", "zip": "48427", "zip5": "48427", "phone": "8103762395", "fax": "8103762305"}}}