{"licNum": "15679", "npi": "1023156635", "credential": "DDS", "class": "Dentist", "specialization": "General Practice", "gender": "M", "updated": "6/17/2008", "name": {"first": "JOSEPH", "last": "SERRA", "middle": "MICHAEL", "prefix": "DR."}, "orgName": "", "tin": "1023156635156", "loc": {"lat": 42.47, "lon": -83.49}, "addr": {"mail": {"street_1": "21600 PHILLIP DR", "city": "NOVI", "state": "MI", "zip": "483755143", "zip5": "48375", "phone": "2487671520"}, "bus": {"street_1": "42010 GRAND RIVER AVE", "city": "NOVI", "state": "MI", "zip": "483751831", "zip5": "48375", "phone": "2487671520"}}}