{"licNum": "16961", "npi": "1912165556", "credential": "DDS", "class": "Dentist", "specialization": "", "gender": "F", "updated": "5/30/2008", "name": {"first": "MICHEL", "last": "WICKSALL", "middle": "MARIE", "prefix": "MISS"}, "orgName": "", "tin": "1912165556169", "loc": {"lat": 42.96, "lon": -85.65}, "addr": {"mail": {"street_1": "4500 CASCADE RD SE", "street_2": "200", "city": "GRAND RAPIDS", "state": "MI", "zip": "49546", "zip5": "49546", "phone": "6169759700", "fax": "6169759750"}, "bus": {"street_1": "4500 CASCADE RD SE", "street_2": "200", "city": "GRAND RAPIDS", "state": "MI", "zip": "49546", "zip5": "49546", "phone": "6169759700", "fax": "6169759750"}}}