{"licNum": "18003", "npi": "1679540421", "credential": "DDS", "class": "Dentist", "specialization": "", "gender": "F", "updated": "9/9/2015", "name": {"first": "LAILA", "last": "CARR", "middle": "SUZETTE", "prefix": "DR."}, "orgName": "", "tin": "1679540421180", "loc": {"lat": 42.2, "lon": -83.48}, "addr": {"mail": {"street_1": "256 3RD ST", "city": "BELLEVILLE", "state": "MI", "zip": "481112606", "zip5": "48111", "phone": "7346979200", "fax": "7346979293"}, "bus": {"street_1": "256 3RD ST", "city": "BELLEVILLE", "state": "MI", "zip": "481112606", "zip5": "48111", "phone": "7346979200", "fax": "7346979293"}}}