{"licNum": "2091010786", "npi": "1326235193", "credential": "DDS", "class": "Dentist", "specialization": "General Practice", "gender": "M", "updated": "9/26/2007", "name": {"first": "MARTIN", "last": "CIRULIS", "middle": "R"}, "orgName": "", "tin": "1326235193209", "loc": {"lat": 45.07, "lon": -83.43}, "addr": {"mail": {"street_1": "320 LONG RAPIDS PLZ", "city": "ALPENA", "state": "MI", "zip": "497071374", "zip5": "49707", "phone": "9893542108"}, "bus": {"street_1": "320 LONG RAPIDS PLZ", "city": "ALPENA", "state": "MI", "zip": "497071374", "zip5": "49707", "phone": "9893542108"}}}