{"licNum": "2177", "npi": "1962552927", "credential": "DDS", "class": "Dentist", "specialization": "Dental Public Health", "gender": "M", "updated": "7/8/2007", "name": {"first": "BARRY", "last": "HOPPER", "middle": "L", "prefix": "DR."}, "orgName": "", "tin": "1962552927217", "loc": {"lat": 36.53, "lon": -82.32}, "addr": {"mail": {"street_1": "133 SPANISH OAK RD", "city": "BRISTOL", "state": "TN", "zip": "376202722", "zip5": "37620", "phone": "4239687224"}, "bus": {"street_1": "975 EMERGENCY RD.", "city": "BLOUNTVILLE", "state": "TN", "zip": "376170630", "zip5": "37617", "phone": "4233232796"}}}