{"licNum": "2486", "npi": "1649311416", "credential": "DMD", "class": "Dentist", "specialization": "General Practice", "gender": "M", "updated": "7/9/2007", "name": {"first": "JOHN", "last": "GRAMMER", "middle": "STANLEY", "prefix": "DR."}, "orgName": "", "tin": "1649311416248", "loc": {"lat": 35.5, "lon": -92.03}, "addr": {"mail": {"street_1": "1203 W MAIN ST", "city": "HEBER SPRINGS", "state": "AR", "zip": "725432830", "zip5": "72543", "phone": "5013622845"}, "bus": {"street_1": "1203 W MAIN ST", "city": "HEBER SPRINGS", "state": "AR", "zip": "725432830", "zip5": "72543", "phone": "5013622845"}}}