{"licNum": "2751", "npi": "1376611269", "credential": "DDS", "class": "Dentist", "specialization": "General Practice", "gender": "M", "updated": "7/8/2007", "name": {"first": "BRUCE", "last": "BELL", "middle": "A.", "prefix": "DR."}, "orgName": "", "tin": "1376611269275", "loc": {"lat": 36.11, "lon": -83.48}, "addr": {"mail": {"street_1": "683 E BROADWAY BLVD", "city": "JEFFERSON CITY", "state": "TN", "zip": "377604906", "zip5": "37760", "phone": "8654758331", "fax": "8654754631"}, "bus": {"street_1": "683 E BROADWAY BLVD", "city": "JEFFERSON CITY", "state": "TN", "zip": "377604906", "zip5": "37760", "phone": "8654758331", "fax": "8654754631"}}}