{"licNum": "2901016939", "npi": "1922135417", "credential": "DDS", "class": "Dentist", "specialization": "General Practice", "gender": "M", "updated": "12/10/2014", "name": {"first": "TIMOTHY", "last": "HARBIN", "middle": "MARTIN", "prefix": "DR."}, "orgName": "", "tin": "1922135417290", "loc": {"lat": 45.02, "lon": -84.67}, "addr": {"mail": {"street_1": "785 E-M32 HWY", "city": "GAYLORD", "state": "MI", "zip": "49735", "zip5": "49735", "phone": "9894482664", "fax": "9894482666"}, "bus": {"street_1": "785 E M 32", "city": "GAYLORD", "state": "MI", "zip": "497358790", "zip5": "49735", "phone": "9894482664", "fax": "9894482666"}}}