{"licNum": "2901008858", "npi": "1962588202", "credential": "\"D.D.S., M.S.\"", "class": "Dentist", "specialization": "Orthodontics and Dentofacial Orthopedics", "gender": "M", "updated": "7/8/2007", "name": {"first": "JOHN", "last": "MARX", "middle": "D.", "prefix": "DR."}, "orgName": "", "tin": "1962588202290", "loc": {"lat": 42.5, "lon": -83.1}, "addr": {"mail": {"street_1": "30201 DEQUINDRE RD", "city": "MADISON HEIGHTS", "state": "MI", "zip": "480712282", "zip5": "48071", "phone": "2485882020", "fax": "2485885610"}, "bus": {"street_1": "30201 DEQUINDRE RD", "city": "MADISON HEIGHTS", "state": "MI", "zip": "480712282", "zip5": "48071", "phone": "2485882020", "fax": "2485885610"}}}