{"licNum": "2901022574", "npi": "1801372008", "credential": "DDS", "class": "Dentist", "specialization": "", "gender": "M", "updated": "7/11/2018", "name": {"first": "JOSEPH", "last": "FAZZIO", "prefix": "DR."}, "orgName": "", "tin": "1801372008290", "loc": {"lat": 42.27, "lon": -83.73}, "addr": {"mail": {"street_1": "465 HARBOR WAY", "city": "ANN ARBOR", "state": "MI", "zip": "481036666", "zip5": "48103", "phone": "2489612991"}, "bus": {"street_1": "465 HARBOR WAY", "city": "ANN ARBOR", "state": "MI", "zip": "481036666", "zip5": "48103", "phone": "2489612991"}}}