{"licNum": "2901016366", "npi": "1316028046", "credential": "D.D.S.", "class": "Dentist", "specialization": "General Practice", "gender": "M", "updated": "7/8/2007", "name": {"first": "DARRIN", "last": "GOURLAY", "prefix": "DR."}, "orgName": "", "tin": "1316028046290", "loc": {"lat": 41.83, "lon": -86.24}, "addr": {"mail": {"street_1": "104 GRANT ST", "city": "NILES", "state": "MI", "zip": "491202201", "zip5": "49120", "phone": "2696831077"}, "bus": {"street_1": "104 GRANT ST", "city": "NILES", "state": "MI", "zip": "491202201", "zip5": "49120", "phone": "2696831077"}}}