{"licNum": "2901020066", "npi": "1205066800", "credential": "DDS", "class": "Dentist", "specialization": "Oral and Maxillofacial Surgery", "gender": "M", "updated": "7/17/2009", "name": {"first": "ERIK", "last": "WARREN"}, "orgName": "", "tin": "1205066800290", "loc": {"lat": 42.5, "lon": -83.1}, "addr": {"mail": {"street_1": "27351 DEQUINDRE ROAD", "city": "MADISON HEIGHTS", "state": "MI", "zip": "48071", "zip5": "48071", "phone": "2489677795", "fax": "2489677794"}, "bus": {"street_1": "27351 DEQUINDRE ROAD", "city": "MADISON HEIGHTS", "state": "MI", "zip": "48071", "zip5": "48071", "phone": "2489677795", "fax": "2489677794"}}}