{"licNum": "2901014377", "npi": "1023186368", "credential": "DDS", "class": "Dentist", "specialization": "", "gender": "M", "updated": "7/8/2007", "name": {"first": "BRIAN", "last": "BAILEY", "middle": "ELDON", "prefix": "DR."}, "orgName": "", "tin": "1023186368290", "loc": {"lat": 43.62, "lon": -84.22}, "addr": {"mail": {"street_1": "308 DARTMOUTH DRIVE", "street_2": "SUITE 1", "city": "MIDLAND", "state": "MI", "zip": "48640", "zip5": "48640", "phone": "9896316075", "fax": "9896313116"}, "bus": {"street_1": "308 DARTMOUTH DRIVE", "street_2": "SUITE 1", "city": "MIDLAND", "state": "MI", "zip": "48640", "zip5": "48640", "phone": "9896316075", "fax": "9896313116"}}}