{"licNum": "2901017711", "npi": "1699884767", "credential": "DDS", "class": "Dentist", "specialization": "", "gender": "F", "updated": "9/19/2014", "name": {"first": "DAWLAT", "last": "HASSO", "middle": "G", "prefix": "DR."}, "orgName": "", "tin": "1699884767290", "loc": {"lat": 42.67, "lon": -83.24}, "addr": {"mail": {"street_1": "6323 GLYNDEBOURNE DR", "city": "TROY", "state": "MI", "zip": "480982212", "zip5": "48098", "phone": "2483793093"}, "bus": {"street_1": "4139 BALDWIN RD", "city": "AUBURN HILLS", "state": "MI", "zip": "483261225", "zip5": "48326", "phone": "2483793093"}}}