{"licNum": "2901012956", "npi": "1528162187", "credential": "DDS", "class": "Dentist", "specialization": "General Practice", "gender": "M", "updated": "7/8/2007", "name": {"first": "JON", "last": "MCLAIN", "middle": "B", "prefix": "DR."}, "orgName": "", "tin": "1528162187290", "loc": {"lat": 45.07, "lon": -83.43}, "addr": {"mail": {"street_1": "115 ARBOR LANE", "city": "ALPENA", "state": "MI", "zip": "49707", "zip5": "49707", "phone": "9893545625", "fax": "9893542815"}, "bus": {"street_1": "115 ARBOR LANE", "city": "ALPENA", "state": "MI", "zip": "49707", "zip5": "49707", "phone": "9893545625", "fax": "9893542815"}}}