{"licNum": "31911", "npi": "1902014863", "credential": "RDA", "class": "Dentist", "specialization": "Orthodontics and Dentofacial Orthopedics", "gender": "F", "updated": "7/9/2007", "name": {"first": "SHANNONJ", "last": "FENTON", "middle": "LEE"}, "orgName": "", "tin": "1902014863319", "loc": {"lat": 33.5, "lon": -112.12}, "addr": {"mail": {"street_1": "3530 E MORELAND ST APT 3", "city": "PHOENIX", "state": "AZ", "zip": "850085247", "zip5": "85008", "phone": "4804301172"}, "bus": {"street_1": "3155 W INDIAN SCHOOL RD", "city": "PHOENIX", "state": "AZ", "zip": "850174035", "zip5": "85017", "phone": "6022129533"}}}