{"licNum": "3250", "npi": "1568524056", "credential": "", "class": "Dentist", "specialization": "General Practice", "gender": "M", "updated": "7/8/2007", "name": {"first": "KENNY", "last": "DUFF"}, "orgName": "", "tin": "1568524056325", "loc": {"lat": 35.36, "lon": -94.38}, "addr": {"mail": {"street_1": "8700 S 36TH TER", "city": "FORT SMITH", "state": "AR", "zip": "729088797", "zip5": "72908", "phone": "4796461979"}, "bus": {"street_1": "8700 S 36TH TER", "city": "FORT SMITH", "state": "AR", "zip": "729088797", "zip5": "72908", "phone": "4796461979"}}}