{"licNum": "3352", "npi": "1801068150", "credential": "DDS", "class": "Dentist", "specialization": "", "gender": "M", "updated": "3/27/2008", "name": {"first": "JAMES", "last": "TYUS", "middle": "EDDIE", "prefix": "DR.", "suffix": "I"}, "orgName": "", "tin": "1801068150335", "loc": {"lat": 36.17, "lon": -86.78}, "addr": {"mail": {"street_1": "113 GRAYLYNN DR", "city": "NASHVILLE", "state": "TN", "zip": "372142705", "zip5": "37214", "phone": "6158899777", "fax": "6158899091"}, "bus": {"street_1": "113 GRAYLYNN DR", "city": "NASHVILLE", "state": "TN", "zip": "372142705", "zip5": "37214", "phone": "6158899777", "fax": "6158899091"}}}