{"licNum": "3360", "npi": "1740301514", "credential": "D.D.S.", "class": "Dentist", "specialization": "General Practice", "gender": "F", "updated": "8/2/2011", "name": {"first": "KIMBERLY", "last": "ALBRECHT", "middle": "ANN"}, "orgName": "", "tin": "1740301514336", "loc": {"lat": 33.62, "lon": -112.05}, "addr": {"mail": {"street_1": "15640 N 7TH ST", "street_2": "SUITE A-4", "city": "PHOENIX", "state": "AZ", "zip": "850223512", "zip5": "85022", "phone": "6028436000"}, "bus": {"street_1": "15640 N 7TH ST", "street_2": "SUITE A-4", "city": "PHOENIX", "state": "AZ", "zip": "850223512", "zip5": "85022", "phone": "6028436000"}}}