{"licNum": "3988", "npi": "1568876530", "credential": "DDS", "class": "Dentist", "specialization": "", "gender": "F", "updated": "8/15/2016", "name": {"first": "JESSICA", "last": "TEALE", "middle": "L"}, "orgName": "", "tin": "1568876530398", "loc": {"lat": 34.5, "lon": -93.05}, "addr": {"mail": {"street_1": "315 SECTION LINE RD STE B", "city": "HOT SPRINGS", "state": "AR", "zip": "719136479", "zip5": "71913", "phone": "8702083275"}, "bus": {"street_1": "126 BAY RIDGE LOOP", "city": "HOT SPRINGS", "state": "AR", "zip": "719019272", "zip5": "71901", "phone": "8702083275"}}}