{"licNum": "5341", "npi": "1003997750", "credential": "D.D.S.", "class": "Dentist", "specialization": "General Practice", "gender": "M", "updated": "7/8/2007", "name": {"first": "GARY", "last": "BETZ", "middle": "ARLIN", "prefix": "DR."}, "orgName": "", "tin": "1003997750534", "loc": {"lat": 33.32, "lon": -111.87}, "addr": {"mail": {"street_1": "4741 E MELANIE DR", "city": "CAVE CREEK", "state": "AZ", "zip": "853316289", "zip5": "85331", "phone": "4806590611", "fax": "4806590611"}, "bus": {"street_1": "485 S DOBSON RD", "city": "CHANDLER", "state": "AZ", "zip": "852245602", "zip5": "85224", "phone": "4808219022", "fax": "4808219064"}}}