{"licNum": "5936", "npi": "1528251402", "credential": "DMD", "class": "Dentist", "specialization": "", "gender": "M", "updated": "8/23/2007", "name": {"first": "JOHN", "last": "PATTERSON", "prefix": "DR."}, "orgName": "", "tin": "1528251402593", "loc": {"lat": 33.48, "lon": -111.92}, "addr": {"mail": {"street_1": "34522 N SCOTTSDALE ROAD", "street_2": "SUITE D-5", "city": "SCOTTSDALE", "state": "AZ", "zip": "85266", "zip5": "85266", "phone": "4805951300", "fax": "4805950274"}, "bus": {"street_1": "34522 N SCOTTSDALE RD", "street_2": "SUITE D-5", "city": "SCOTTSDALE", "state": "AZ", "zip": "852661224", "zip5": "85266", "phone": "4805951300", "fax": "4805950274"}}}