{"licNum": "7184", "npi": "1699933317", "credential": "DDS", "class": "Dentist", "specialization": "General Practice", "gender": "M", "updated": "4/29/2013", "name": {"first": "NAMAN", "last": "PATEL", "middle": "BHAILAL", "prefix": "DR."}, "orgName": "", "tin": "1699933317718", "loc": {"lat": 33.34, "lon": -111.81}, "addr": {"mail": {"street_1": "1489 W ELLIOT RD STE 101", "city": "GILBERT", "state": "AZ", "zip": "852335168", "zip5": "85233", "phone": "4805079400", "fax": "4805079474"}, "bus": {"street_1": "1489 W ELLIOT RD", "street_2": "SUITE 101", "city": "GILBERT", "state": "AZ", "zip": "852335168", "zip5": "85233", "phone": "4805079400", "fax": "4805079474"}}}