{"licNum": "8787", "npi": "1093925497", "credential": "\"DDS, MD\"", "class": "Dentist", "specialization": "Oral and Maxillofacial Surgery", "gender": "M", "updated": "8/10/2012", "name": {"first": "TROY", "last": "TRONDSON", "middle": "A"}, "orgName": "", "tin": "1093925497878", "loc": {"lat": 35.74, "lon": -83.97}, "addr": {"mail": {"street_1": "1505 E LAMAR ALEXANDER PKWY", "city": "MARYVILLE", "state": "TN", "zip": "378045131", "zip5": "37804", "phone": "8659838630", "fax": "8659814914"}, "bus": {"street_1": "1505 E LAMAR ALEXANDER PKWY", "city": "MARYVILLE", "state": "TN", "zip": "378045131", "zip5": "37804", "phone": "8659838630", "fax": "8659814914"}}}