{"licNum": "9971", "npi": "1366545527", "credential": "DDS", "class": "Dentist", "specialization": "General Practice", "gender": "M", "updated": "7/8/2007", "name": {"first": "IRVING", "last": "BLAU"}, "orgName": "", "tin": "1366545527997", "loc": {"lat": 42.32, "lon": -83.27}, "addr": {"mail": {"street_1": "3835 SPANISH OAKS DR", "city": "W BLOOMFIELD", "state": "MI", "zip": "483231867", "zip5": "48323"}, "bus": {"street_1": "24415 W WARREN ST", "city": "DEARBORN HTS", "state": "MI", "zip": "481272223", "zip5": "48127", "phone": "3132784470", "fax": "3132780124"}}}