{"licNum": "AZ5398", "npi": "1396967915", "credential": "DDS MS", "class": "Dentist", "specialization": "Endodontics", "gender": "M", "updated": "3/25/2011", "name": {"first": "NEIL", "last": "MILLER", "middle": "THOMAS", "prefix": "DR."}, "orgName": "", "tin": "1396967915AZ5", "loc": {"lat": 33.32, "lon": -111.87}, "addr": {"mail": {"street_1": "595 N DOBSON RD", "street_2": "B 24", "city": "CHANDLER", "state": "AZ", "zip": "85224", "zip5": "85224", "phone": "4806633000", "fax": "4806633003"}, "bus": {"street_1": "595 N DOBSON RD", "street_2": "B 24", "city": "CHANDLER", "state": "AZ", "zip": "85224", "zip5": "85224", "phone": "4806633000", "fax": "4806633003"}}}