{"licNum": "D-7979", "npi": "1689909376", "credential": "DMD", "class": "Dentist", "specialization": "General Practice", "gender": "F", "updated": "6/7/2010", "name": {"first": "MONYA", "last": "PHUNG", "prefix": "DR."}, "orgName": "", "tin": "1689909376D-7", "loc": {"lat": 33.62, "lon": -112.05}, "addr": {"mail": {"street_1": "1 W CAMPBELL AVE APT 2044", "city": "PHOENIX", "state": "AZ", "zip": "850134912", "zip5": "85013", "phone": "5035053381"}, "bus": {"street_1": "475 E BELL RD", "city": "PHOENIX", "state": "AZ", "zip": "850222348", "zip5": "85022", "phone": "5035053381"}}}