{"licNum": "D008375", "npi": "1841553120", "credential": "DMD", "class": "Dentist", "specialization": "Dentist Anesthesiologist", "gender": "M", "updated": "9/3/2015", "name": {"first": "JASON", "last": "BRADY", "middle": "WAYNE", "prefix": "DR."}, "orgName": "", "tin": "1841553120D00", "loc": {"lat": 33.36, "lon": -111.75}, "addr": {"mail": {"street_1": "3967 E LEAH CT", "street_2": "APT 101", "city": "GILBERT", "state": "AZ", "zip": "852340019", "zip5": "85234", "phone": "8587524622", "fax": "8663298262"}, "bus": {"street_1": "3967 E LEAH CT", "street_2": "APT 101", "city": "GILBERT", "state": "AZ", "zip": "852340019", "zip5": "85234", "phone": "8587524622", "fax": "8663298262"}}}