{"licNum": "D010061", "npi": "1114411261", "credential": "DMD", "class": "Dentist", "specialization": "General Practice", "gender": "F", "updated": "6/22/2018", "name": {"first": "LY", "last": "HUYNH", "middle": "KHANH", "prefix": "DR."}, "orgName": "", "tin": "1114411261D01", "loc": {"lat": 33.76, "lon": -112.24}, "addr": {"mail": {"street_1": "6358 W GOLDEN LN", "city": "GLENDALE", "state": "AZ", "zip": "853024434", "zip5": "85302", "phone": "6236986351"}, "bus": {"street_1": "9947 W HAPPY VALLEY RD STE 101", "city": "PEORIA", "state": "AZ", "zip": "85383", "zip5": "85383", "phone": "6235720893"}}}