{"licNum": "D11956", "npi": "1982649984", "credential": "DDS", "class": "Dentist", "specialization": "", "gender": "M", "updated": "7/8/2007", "name": {"first": "JOSHUA", "last": "CAMPBELL", "middle": "DONALD DEL", "prefix": "DR."}, "orgName": "", "tin": "1982649984D11", "loc": {"lat": 44.88, "lon": -94.37}, "addr": {"mail": {"street_1": "2 FRANKLIN ST", "city": "HUTCHINSON", "state": "MN", "zip": "55350", "zip5": "55350", "phone": "3205873993", "fax": "3205870600"}, "bus": {"street_1": "2 FRANKLIN ST", "city": "HUTCHINSON", "state": "MN", "zip": "55350", "zip5": "55350", "phone": "3205873993", "fax": "3205870600"}}}