{"licNum": "D13363", "npi": "1952713026", "credential": "D.D.S.", "class": "Dentist", "specialization": "General Practice", "gender": "M", "updated": "4/24/2017", "name": {"first": "BRENT", "last": "SORENSON", "prefix": "DR."}, "orgName": "", "tin": "1952713026D13", "loc": {"lat": 45.15, "lon": -92.96}, "addr": {"mail": {"street_1": "3045 STANDRIDGE PL", "city": "MAPLEWOOD", "state": "MN", "zip": "551091562", "zip5": "55109"}, "bus": {"street_1": "14688 EVERTON AVE N", "street_2": "SUITE # 104", "city": "HUGO", "state": "MN", "zip": "550386064", "zip5": "55038", "phone": "6512040201"}}}