{"licNum": "DS003776", "npi": "1447267331", "credential": "DDS", "class": "Dentist", "specialization": "", "gender": "M", "updated": "7/8/2007", "name": {"first": "PAUL", "last": "GILLIAM", "middle": "LAWRENCE"}, "orgName": "", "tin": "1447267331DS0", "loc": {"lat": 35.99, "lon": -86.78}, "addr": {"mail": {"street_1": "1749 MALLORY LN", "street_2": "SUITE 245", "city": "BRENTWOOD", "state": "TN", "zip": "370272931", "zip5": "37027", "phone": "6153708945", "fax": "6153700765"}, "bus": {"street_1": "1749 MALLORY LN", "street_2": "SUITE 245", "city": "BRENTWOOD", "state": "TN", "zip": "370272931", "zip5": "37027", "phone": "6153708945", "fax": "6153700765"}}}