{"licNum": "DS3043", "npi": "1285828665", "credential": "DDS", "class": "Dentist", "specialization": "", "gender": "M", "updated": "8/29/2007", "name": {"first": "STEPHEN", "last": "AREHART", "middle": "R", "prefix": "MR."}, "orgName": "", "tin": "1285828665DS3", "loc": {"lat": 35.96, "lon": -84.29}, "addr": {"mail": {"street_1": "1950A OAK RIDGE TRPK", "city": "OAK RIDGE", "state": "TN", "zip": "37830", "zip5": "37830", "phone": "8654823474", "fax": "8654823474"}, "bus": {"street_1": "1950A OAK RIDGE TRPK", "city": "OAK RIDGE", "state": "TN", "zip": "37830", "zip5": "37830", "phone": "8654823474", "fax": "8654823474"}}}