{"licNum": "DS4711", "npi": "1285631135", "credential": "DDS", "class": "Dentist", "specialization": "Oral and Maxillofacial Surgery", "gender": "M", "updated": "10/10/2011", "name": {"first": "MARK", "last": "WIDLOSKI", "middle": "M."}, "orgName": "", "tin": "1285631135DS4", "loc": {"lat": 35.74, "lon": -83.97}, "addr": {"mail": {"street_1": "1505 E LAMAR ALEXANDER PKWY", "city": "MARYVILLE", "state": "TN", "zip": "378045131", "zip5": "37804", "phone": "8659838630", "fax": "8659833616"}, "bus": {"street_1": "1505 E LAMAR ALEXANDER PKWY", "city": "MARYVILLE", "state": "TN", "zip": "378045131", "zip5": "37804", "phone": "8659838630", "fax": "8659833616"}}}