{"licNum": "DS 33226", "npi": "1881967263", "credential": "D.D.S.", "class": "Dentist", "specialization": "General Practice", "gender": "M", "updated": "2/16/2012", "name": {"first": "MARK", "last": "SMITH", "middle": "STEVEN", "prefix": "DR."}, "orgName": "", "tin": "1881967263DS3", "loc": {"lat": 35.08, "lon": -89.79}, "addr": {"mail": {"street_1": "7685 WOLF RIVER CIR STE 102", "city": "GERMANTOWN", "state": "TN", "zip": "381381749", "zip5": "38138", "phone": "9017674882"}, "bus": {"street_1": "7685 WOLF RIVER CIR STE 102", "city": "GERMANTOWN", "state": "TN", "zip": "381381749", "zip5": "38138", "phone": "9017674882"}}}